brainglobe_registration/__init__.py
brainglobe_registration/automated_target_selection.py
brainglobe_registration/napari.yaml
brainglobe_registration/registration_widget.py
brainglobe_registration/sample_data.py
brainglobe_registration/similarity_metrics.py
brainglobe_registration/elastix/__init__.py
brainglobe_registration/elastix/register.py
brainglobe_registration/parameters/ara_tools/affine.txt
brainglobe_registration/parameters/ara_tools/bspline.txt
brainglobe_registration/parameters/brainglobe_registration/affine.txt
brainglobe_registration/parameters/brainglobe_registration/automated_reg_affine.txt
brainglobe_registration/parameters/brainglobe_registration/bspline.txt
brainglobe_registration/parameters/brainregister_IBL/affine.txt
brainglobe_registration/parameters/brainregister_IBL/bspline.txt
brainglobe_registration/parameters/elastix_default/affine.txt
brainglobe_registration/parameters/elastix_default/bspline.txt
brainglobe_registration/resources/sample_3d.tif
brainglobe_registration/resources/sample_hipp.tif
brainglobe_registration/utils/__init__.py
brainglobe_registration/utils/logging.py
brainglobe_registration/utils/preprocess.py
brainglobe_registration/utils/transforms.py
brainglobe_registration/utils/utils.py
brainglobe_registration/widgets/__init__.py
brainglobe_registration/widgets/adjust_moving_image_view.py
brainglobe_registration/widgets/parameter_list_view.py
brainglobe_registration/widgets/select_images_view.py
brainglobe_registration/widgets/target_selection_widget.py
brainglobe_registration/widgets/transform_select_view.py
brainglobe_registration-0.0.5.dist-info/licenses/LICENSE
brainglobe_registration-0.0.5.dist-info/METADATA
brainglobe_registration-0.0.5.dist-info/WHEEL
brainglobe_registration-0.0.5.dist-info/entry_points.txt
brainglobe_registration-0.0.5.dist-info/top_level.txt
brainglobe_registration-0.0.5.dist-info/RECORD
