Metadata-Version: 2.4
Name: brainglobe-registration
Version: 0.0.5
Summary: A napari plugin for registration to a  BrainGlobe atlas.
Author-email: Brainglobe Developers <hello@brainglobe.info>
License: BSD-3-Clause
Project-URL: Homepage, https://brainglobe.info
Project-URL: Bug Tracker, https://github.com/brainglobe/brainglobe-registration/issues
Project-URL: Documentation, https://github.com/brainglobe/brainglobe-registration#README.md
Project-URL: Source Code, https://github.com/brainglobe/brainglobe-registration
Project-URL: User Support, https://forum.image.sc/tag/brainglobe
Classifier: Development Status :: 2 - Pre-Alpha
Classifier: Framework :: napari
Classifier: Intended Audience :: Science/Research
Classifier: Programming Language :: Python
Classifier: Programming Language :: Python :: 3
Classifier: Programming Language :: Python :: 3.11
Classifier: Programming Language :: Python :: 3.12
Classifier: Programming Language :: Python :: 3.13
Classifier: Operating System :: OS Independent
Classifier: License :: OSI Approved :: BSD License
Classifier: Topic :: Scientific/Engineering :: Image Processing
Requires-Python: >=3.11
License-File: LICENSE
Requires-Dist: napari!=0.6.0,>=0.4.18
Requires-Dist: bayesian-optimization
Requires-Dist: brainglobe-atlasapi
Requires-Dist: brainglobe-utils>=0.4.3
Requires-Dist: dask
Requires-Dist: dask-image
Requires-Dist: fancylog
Requires-Dist: itk-elastix
Requires-Dist: lxml_html_clean
Requires-Dist: numpy
Requires-Dist: pandas
Requires-Dist: pytransform3d
Requires-Dist: qtpy
Requires-Dist: qt-niu
Requires-Dist: scikit-image
Requires-Dist: scipy
Requires-Dist: tifffile
Provides-Extra: dev
Requires-Dist: pytest; extra == "dev"
Requires-Dist: pytest-cov; extra == "dev"
Requires-Dist: pytest-mock; extra == "dev"
Requires-Dist: pytest-qt; extra == "dev"
Requires-Dist: coverage; extra == "dev"
Requires-Dist: tox; extra == "dev"
Requires-Dist: black; extra == "dev"
Requires-Dist: mypy; extra == "dev"
Requires-Dist: pre-commit; extra == "dev"
Requires-Dist: ruff; extra == "dev"
Requires-Dist: setuptools_scm; extra == "dev"
Requires-Dist: pyqt5; extra == "dev"
Dynamic: license-file
